python_licensing/__init__.py
python_licensing/python_licensing.py
python_licensing-0.1.1.dist-info/METADATA
python_licensing-0.1.1.dist-info/WHEEL
python_licensing-0.1.1.dist-info/top_level.txt
python_licensing-0.1.1.dist-info/RECORD
